[
    {
        "name": "Get remote connection file (RDP)",
        "icon": "fa fa-arrow-down",
        "fileName": "createRDPFile.ps1",
        "actionType": "File"
    },
    {
        "name": "Start or stop the VM",
        "icon": "fa fa-power-off",
        "fileName": "turnVMOnOff.ps1",
        "actionType": "Notification"
    },
    {
        "name": "Check if VM is running",
        "icon": "fa fa-question-circle",
        "fileName": "checkVMOnOff.ps1",
        "actionType": "Notification"
    },
    {
        "name": "Check UPGRADE WORKS",
        "icon": "fa fa-windows",
        "fileName": "checkVMOnOff.ps1",
        "actionType": "Notification"
    }
]